dyrun/__init__.py
dyrun/cli.py
dyrun/dyrun.ipynb
dyrun/dyrun.py
dyrun/blocks/README.md
dyrun/blocks/__init__.py
dyrun/blocks/comp_neuro_blocks.py
dyrun/blocks/general_blocks.py
dyrun/core/README.md
dyrun/core/__init__.py
dyrun/core/caller/__init__.py
dyrun/core/caller/dynamic_engine.py
dyrun/core/caller/scope_engine.py
dyrun/core/lib/__init__.py
dyrun/core/lib/core_library.py
dyrun/core/lib/required_libraries.py
dyrun/core/lib/eclib/README.md
dyrun/core/lib/eclib/__init__.py
dyrun/core/lib/eclib/dyn_elgamal.py
dyrun/core/lib/eclib/elgamal.py
dyrun/core/lib/eclib/gsw.py
dyrun/core/lib/eclib/gsw_lwe.py
dyrun/core/lib/eclib/modutils.py
dyrun/core/lib/eclib/numutils.py
dyrun/core/lib/eclib/paillier.py
dyrun/core/lib/eclib/primeutils.py
dyrun/core/lib/eclib/randutils.py
dyrun/core/lib/eclib/regev.py
dyrun/data/README.md
dyrun/data/inputs/README.md
dyrun/data/outputs/README.md
dyrun-1.1.11.dist-info/LICENSE.md
dyrun-1.1.11.dist-info/METADATA
dyrun-1.1.11.dist-info/WHEEL
dyrun-1.1.11.dist-info/entry_points.txt
dyrun-1.1.11.dist-info/top_level.txt
dyrun-1.1.11.dist-info/RECORD
