Metadata-Version: 2.1
Name: dyrun
Version: 1.1.11
Summary: Easy way to simulation
Home-page: https://github.com/abolfazldelavar/dyrun
Author: Abolfazl Delavar
Author-email: faryadell@gmail.com
License: MIT
Keywords: Control,Simulation,Academic,Mathematics,Differential,Closed-loop,Numberical calculation
Platform: UNKNOWN
Classifier: Programming Language :: Python :: 3
Classifier: License :: OSI Approved :: MIT License
Classifier: Operating System :: OS Independent
Requires-Python: >=3.6
Requires-Dist: numpy
Requires-Dist: pandas
Requires-Dist: matplotlib
Requires-Dist: control
Requires-Dist: pyqt5
Requires-Dist: opencv-python
Requires-Dist: click
